scene_cutter/__init__.py
scene_cutter/scene_cutter.py
scene_cutter-0.0.9.dist-info/LICENSE
scene_cutter-0.0.9.dist-info/METADATA
scene_cutter-0.0.9.dist-info/WHEEL
scene_cutter-0.0.9.dist-info/top_level.txt
scene_cutter-0.0.9.dist-info/RECORD
