Metadata-Version: 2.1
Name: scene-cutter
Version: 0.0.9
Summary: Trim scenes from a video - based on ffmpeg
Home-page: https://github.com/Zselter07/scene_cutter
Author: Péntek Zsolt
License: UNKNOWN
Platform: UNKNOWN
Classifier: Programming Language :: Python :: 3
Classifier: License :: OSI Approved :: MIT License
Classifier: Operating System :: OS Independent
Requires-Python: >=3.6
Requires-Dist: kcu
